CMakeLists.txt
COPYING
COPYING.BSD
COPYING.LGPL
LICENSE
MANIFEST.in
README
VERSION_INFO
dopy.sh
genversion.sh
install.sh
publish.sh
setup.py
bindings/CMakeLists.txt
bindings/python/.gitattributes
bindings/python/.gitignore
bindings/python/CMakeLists.txt
bindings/python/MANIFEST.in
bindings/python/README.rst
bindings/python/VERSION
bindings/python/setup.py.in
bindings/python/setup_pypi.py
bindings/python/docs/Makefile
bindings/python/docs/ReleaseNotes.txt
bindings/python/docs/source/conf.py
bindings/python/docs/source/examples.rst
bindings/python/docs/source/gettingstarted.rst
bindings/python/docs/source/index.rst
bindings/python/docs/source/install.rst
bindings/python/docs/source/.static/css/custom.css
bindings/python/docs/source/.static/img/favicon.ico
bindings/python/docs/source/.static/img/xrootd-200x68.png
bindings/python/docs/source/.templates/layout.html
bindings/python/docs/source/examples/copyprocess.rst
bindings/python/docs/source/examples/file.rst
bindings/python/docs/source/examples/filesystem.rst
bindings/python/docs/source/modules/client/copyprocess.rst
bindings/python/docs/source/modules/client/file.rst
bindings/python/docs/source/modules/client/filesystem.rst
bindings/python/docs/source/modules/client/flags.rst
bindings/python/docs/source/modules/client/responses.rst
bindings/python/docs/source/modules/client/url.rst
bindings/python/docs/source/modules/client/utils.rst
bindings/python/examples/copy.py
bindings/python/examples/copyprocess.py
bindings/python/examples/dirlist.py
bindings/python/examples/fcntl.py
bindings/python/examples/fcntl_async.py
bindings/python/examples/fileproperties.py
bindings/python/examples/filesystemproperties.py
bindings/python/examples/iterate.py
bindings/python/examples/locate.py
bindings/python/examples/mkdir.py
bindings/python/examples/mv.py
bindings/python/examples/query.py
bindings/python/examples/read.py
bindings/python/examples/readchunks.py
bindings/python/examples/readlines.py
bindings/python/examples/rm.py
kjpyxrootd.egg-info/PKG-INFO
kjpyxrootd.egg-info/SOURCES.txt
kjpyxrootd.egg-info/dependency_links.txt
kjpyxrootd.egg-info/top_level.txt
