Metadata-Version: 1.0
Name: kjpyxrootd
Version: 20180627.3
Summary: XRootD with Python bindings
Home-page: http://xrootd.org
Author: XRootD Developers
Author-email: xrootd-dev@slac.stanford.edu
License: LGPLv3+
Platform: UNKNOWN
